SimpleEvents/__init__.py
Simple_Events-1.0.2.dist-info/LICENSE
Simple_Events-1.0.2.dist-info/METADATA
Simple_Events-1.0.2.dist-info/WHEEL
Simple_Events-1.0.2.dist-info/top_level.txt
Simple_Events-1.0.2.dist-info/RECORD
