Metadata-Version: 2.1
Name: Simple-Events
Version: 1.0.2
Summary: A simple library that implements a basic event system
Home-page: https://github.com/Vladislav-Martian/SimpleEvents
Author: Vladislav Martian
Author-email: me.as.martian@gmail.com
License: UNKNOWN
Project-URL: Bug Tracker, https://github.com/Vladislav-Martian/SimpleEvents/issues
Platform: UNKNOWN
Classifier: Programming Language :: Python :: 3
Classifier: License :: OSI Approved :: MIT License
Classifier: Operating System :: OS Independent
Requires-Python: >=3.6
License-File: LICENSE
